{
  "network_type": "EVM",
  "slug": "arbitrum_one",
  "name": "Arbitrum One",
  "rpc_urls": [
    {
      "type_": "rpc",
      "url": {
        "type": "plain",
        "value": "https://arb1.arbitrum.io/rpc"
      },
      "weight": 100
    }
  ],
  "chain_id": 42161,
  "block_time_ms": 250,
  "confirmation_blocks": 12,
  "cron_schedule": "0 */1 * * * *",
  "max_past_blocks": 750,
  "store_blocks": false,
  "recovery_config": {
    "enabled": false,
    "cron_schedule": "0 */5 * * * *",
    "max_blocks_per_run": 100,
    "max_block_age": 5000,
    "max_retries": 3,
    "retry_delay_ms": 1000
  }
}
